[
  {
    "_id": {
      "$oid": "632f3dc1b4f33b52fcc7fa17"
    },
    "title": "Brown eggs",
    "category": "dairy",
    "description": "Raw organic brown eggs in a basket",
    "image": {
      "url": "http://localhost:4000/images/0.jpg",
      "name": ""
    },
    "stock": 0,
    "price": 28.1,
    "currency": {
      "name": "US Dollar",
      "code": "USD",
      "symbol": "$",
      "symbolNative": "$",
      "decimalDigits": 2,
      "rounding": 0,
      "namePlural": "US dollars"
    },
    "rating": 4,
    "slug": "brown-eggs",
    "reviews": [],
    "createdAt": {
      "$date": {
        "$numberLong": "1665046691343"
      }
    },
    "updatedAt": {
      "$date": {
        "$numberLong": "1666350016892"
      }
    },
    "discount": null
  },
  {
    "_id": {
      "$oid": "632f3dc1b4f33b52fcc7fa18"
    },
    "title": "Sweet fresh stawberry",
    "category": "fruit",
    "slug": "sweet-fresh-stawberry",
    "description": "Sweet fresh stawberry on the wooden table",
    "image": {
      "url": "http://localhost:4000/images/1.jpg",
      "name": ""
    },
    "stock": 15,
    "price": 29.45,
    "currency": {
      "name": "US Dollar",
      "code": "USD",
      "symbol": "$",
      "symbolNative": "$",
      "decimalDigits": 2,
      "rounding": 0,
      "namePlural": "US dollars"
    },
    "rating": 4,
    "reviews": [],
    "createdAt": {
      "$date": {
        "$numberLong": "1665046691343"
      }
    },
    "updatedAt": {
      "$date": {
        "$numberLong": "1665046691343"
      }
    },
    "discount": null
  },
  {
    "_id": {
      "$oid": "632f3dc1b4f33b52fcc7fa19"
    },
    "title": "Asparagus",
    "category": "vegetable",
    "description": "Asparagus with ham on the wooden table",
    "image": {
      "url": "http://localhost:4000/images/2.jpg",
      "name": ""
    },
    "stock": 2,
    "slug": "asparagus",
    "price": 18.95,
    "currency": {
      "name": "US Dollar",
      "code": "USD",
      "symbol": "$",
      "symbolNative": "$",
      "decimalDigits": 2,
      "rounding": 0,
      "namePlural": "US dollars"
    },
    "rating": 3,
    "reviews": [],
    "createdAt": {
      "$date": {
        "$numberLong": "1665046691343"
      }
    },
    "updatedAt": {
      "$date": {
        "$numberLong": "1665046691343"
      }
    },
    "discount": null
  },
  {
    "_id": {
      "$oid": "632f3dc1b4f33b52fcc7fa1a"
    },
    "title": "Green smoothie",
    "category": "dairy",
    "description": "Glass of green smoothie with quail egg's yolk, served with cocktail tube, green apple and baby spinach leaves over tin surface.",
    "image": {
      "url": "http://localhost:4000/images/3.jpg",
      "name": ""
    },
    "stock": 4,
    "slug": "green-smoothie",
    "price": 17.68,
    "currency": {
      "name": "US Dollar",
      "code": "USD",
      "symbol": "$",
      "symbolNative": "$",
      "decimalDigits": 2,
      "rounding": 0,
      "namePlural": "US dollars"
    },
    "rating": 4,
    "reviews": [],
    "createdAt": {
      "$date": {
        "$numberLong": "1665046691343"
      }
    },
    "updatedAt": {
      "$date": {
        "$numberLong": "1665046691343"
      }
    },
    "discount": null
  },
  {
    "_id": {
      "$oid": "632f3dc1b4f33b52fcc7fa1b"
    },
    "title": "Raw legums",
    "category": "vegetable",
    "description": "Raw legums on the wooden table",
    "image": {
      "url": "http://localhost:4000/images/4.jpg",
      "name": ""
    },
    "stock": 20,
    "price": 17.11,
    "currency": {
      "name": "US Dollar",
      "code": "USD",
      "symbol": "$",
      "symbolNative": "$",
      "decimalDigits": 2,
      "rounding": 0,
      "namePlural": "US dollars"
    },
    "slug": "raw-legums",
    "rating": 2,
    "reviews": [],
    "createdAt": {
      "$date": {
        "$numberLong": "1665046691343"
      }
    },
    "updatedAt": {
      "$date": {
        "$numberLong": "1665046691343"
      }
    },
    "discount": null
  },
  {
    "_id": {
      "$oid": "632f3dc1b4f33b52fcc7fa1c"
    },
    "title": "Baking cake",
    "category": "dairy",
    "description": "Baking cake in rural kitchen - dough  recipe ingredients (eggs, flour, sugar) on vintage wooden table from above.",
    "image": {
      "url": "http://localhost:4000/images/5.jpg",
      "name": ""
    },
    "slug": "baking-cake",
    "stock": 8,
    "price": 11.14,
    "currency": {
      "name": "US Dollar",
      "code": "USD",
      "symbol": "$",
      "symbolNative": "$",
      "decimalDigits": 2,
      "rounding": 0,
      "namePlural": "US dollars"
    },
    "rating": 4,
    "reviews": [],
    "createdAt": {
      "$date": {
        "$numberLong": "1665046691343"
      }
    },
    "updatedAt": {
      "$date": {
        "$numberLong": "1665046691343"
      }
    },
    "discount": null
  },
  {
    "_id": {
      "$oid": "632f3dc1b4f33b52fcc7fa1d"
    },
    "title": "Pesto with basil",
    "category": "vegetable",
    "description": "Italian traditional pesto with basil, chesse and oil",
    "image": {
      "url": "http://localhost:4000/images/6.jpg",
      "name": ""
    },
    "slug": "pesto-with-basil",
    "stock": 10,
    "price": 18.19,
    "currency": {
      "name": "US Dollar",
      "code": "USD",
      "symbol": "$",
      "symbolNative": "$",
      "decimalDigits": 2,
      "rounding": 0,
      "namePlural": "US dollars"
    },
    "rating": 2,
    "reviews": [],
    "createdAt": {
      "$date": {
        "$numberLong": "1665046691343"
      }
    },
    "updatedAt": {
      "$date": {
        "$numberLong": "1665046691343"
      }
    },
    "discount": null
  },
  {
    "_id": {
      "$oid": "632f3dc1b4f33b52fcc7fa1e"
    },
    "title": "Hazelnut in black ceramic bowl",
    "category": "vegetable",
    "description": "Hazelnut in black ceramic bowl on old wooden background. forest wealth. rustic style. selective focus",
    "image": {
      "url": "http://localhost:4000/images/7.jpg",
      "name": ""
    },
    "slug": "hazelnut-in-black-ceramic-bowl",
    "stock": 6,
    "price": 27.35,
    "currency": {
      "name": "US Dollar",
      "code": "USD",
      "symbol": "$",
      "symbolNative": "$",
      "decimalDigits": 2,
      "rounding": 0,
      "namePlural": "US dollars"
    },
    "rating": 0,
    "reviews": [],
    "createdAt": {
      "$date": {
        "$numberLong": "1665046691343"
      }
    },
    "updatedAt": {
      "$date": {
        "$numberLong": "1665046691343"
      }
    },
    "discount": null
  },
  {
    "_id": {
      "$oid": "632f3dc1b4f33b52fcc7fa1f"
    },
    "title": "Fresh stawberry",
    "category": "fruit",
    "description": "Sweet fresh stawberry on the wooden table",
    "image": {
      "url": "http://localhost:4000/images/8.jpg",
      "name": ""
    },
    "slug": "fresh-stawberry",
    "stock": 33,
    "price": 28.59,
    "currency": {
      "name": "US Dollar",
      "code": "USD",
      "symbol": "$",
      "symbolNative": "$",
      "decimalDigits": 2,
      "rounding": 0,
      "namePlural": "US dollars"
    },
    "rating": 4,
    "reviews": [],
    "createdAt": {
      "$date": {
        "$numberLong": "1665046691343"
      }
    },
    "updatedAt": {
      "$date": {
        "$numberLong": "1665046691343"
      }
    },
    "discount": null
  },
  {
    "_id": {
      "$oid": "632f3dc1b4f33b52fcc7fa20"
    },
    "title": "Lemon and salt",
    "category": "fruit",
    "description": "Rosemary, lemon and salt on the table",
    "slug": "lemon-and-salt",
    "image": {
      "url": "http://localhost:4000/images/9.jpg",
      "name": ""
    },
    "stock": 55,
    "price": 15.79,
    "currency": {
      "name": "US Dollar",
      "code": "USD",
      "symbol": "$",
      "symbolNative": "$",
      "decimalDigits": 2,
      "rounding": 0,
      "namePlural": "US dollars"
    },
    "reviews": [],
    "rating": 5,
    "createdAt": {
      "$date": {
        "$numberLong": "1665046691343"
      }
    },
    "updatedAt": {
      "$date": {
        "$numberLong": "1665046691343"
      }
    },
    "discount": null
  },
  {
    "_id": {
      "$oid": "632f3dc1b4f33b52fcc7fa21"
    },
    "title": "Homemade bread",
    "category": "bakery",
    "description": "Homemade bread",
    "image": {
      "url": "http://localhost:4000/images/10.jpg",
      "name": ""
    },
    "slug": "homemade-bread",
    "stock": 64,
    "price": 17.48,
    "currency": {
      "name": "US Dollar",
      "code": "USD",
      "symbol": "$",
      "symbolNative": "$",
      "decimalDigits": 2,
      "rounding": 0,
      "namePlural": "US dollars"
    },
    "rating": 3,
    "reviews": [],
    "createdAt": {
      "$date": {
        "$numberLong": "1665046691343"
      }
    },
    "updatedAt": {
      "$date": {
        "$numberLong": "1665046691343"
      }
    },
    "discount": null
  },
  {
    "_id": {
      "$oid": "632f3dc1b4f33b52fcc7fa22"
    },
    "title": "Legums",
    "category": "vegetable",
    "description": "Cooked legums on the wooden table",
    "image": {
      "url": "http://localhost:4000/images/11.jpg",
      "name": ""
    },
    "slug": "legums",
    "stock": 35,
    "price": 14.77,
    "currency": {
      "name": "US Dollar",
      "code": "USD",
      "symbol": "$",
      "symbolNative": "$",
      "decimalDigits": 2,
      "rounding": 0,
      "namePlural": "US dollars"
    },
    "rating": 0,
    "reviews": [],
    "createdAt": {
      "$date": {
        "$numberLong": "1665046691343"
      }
    },
    "updatedAt": {
      "$date": {
        "$numberLong": "1665046691343"
      }
    },
    "discount": null
  },
  {
    "_id": {
      "$oid": "632f3dc1b4f33b52fcc7fa23"
    },
    "title": "Fresh tomato",
    "category": "vegetable",
    "description": "Fresh tomato juice with basil",
    "image": {
      "url": "http://localhost:4000/images/12.jpg",
      "name": ""
    },
    "stock": 77,
    "slug": "fresh-tomato",
    "price": 16.3,
    "currency": {
      "name": "US Dollar",
      "code": "USD",
      "symbol": "$",
      "symbolNative": "$",
      "decimalDigits": 2,
      "rounding": 0,
      "namePlural": "US dollars"
    },
    "rating": 2,
    "reviews": [],
    "createdAt": {
      "$date": {
        "$numberLong": "1665046691343"
      }
    },
    "updatedAt": {
      "$date": {
        "$numberLong": "1665046691343"
      }
    },
    "discount": null
  },
  {
    "_id": {
      "$oid": "632f3dc1b4f33b52fcc7fa24"
    },
    "title": "Healthy breakfast",
    "category": "fruit",
    "description": "Healthy breakfast set. rice cereal or porridge with berries and honey over rustic wood background",
    "image": {
      "url": "http://localhost:4000/images/13.jpg",
      "name": ""
    },
    "slug": "healthy-breakfast",
    "stock": 13,
    "price": 13.02,
    "currency": {
      "name": "US Dollar",
      "code": "USD",
      "symbol": "$",
      "symbolNative": "$",
      "decimalDigits": 2,
      "rounding": 0,
      "namePlural": "US dollars"
    },
    "rating": 2,
    "reviews": [],
    "createdAt": {
      "$date": {
        "$numberLong": "1665046691343"
      }
    },
    "updatedAt": {
      "$date": {
        "$numberLong": "1665046691343"
      }
    },
    "discount": null
  },
  {
    "_id": {
      "$oid": "632f3dc1b4f33b52fcc7fa25"
    },
    "title": "Green beans",
    "category": "vegetable",
    "description": "Raw organic green beans ready to eat",
    "image": {
      "url": "http://localhost:4000/images/14.jpg",
      "name": ""
    },
    "slug": "green-beans",
    "stock": 41,
    "price": 28.79,
    "currency": {
      "name": "US Dollar",
      "code": "USD",
      "symbol": "$",
      "symbolNative": "$",
      "decimalDigits": 2,
      "rounding": 0,
      "namePlural": "US dollars"
    },
    "rating": 1,
    "reviews": [],
    "createdAt": {
      "$date": {
        "$numberLong": "1665046691343"
      }
    },
    "updatedAt": {
      "$date": {
        "$numberLong": "1665046691343"
      }
    },
    "discount": null
  },
  {
    "_id": {
      "$oid": "632f3dc1b4f33b52fcc7fa26"
    },
    "title": "Baked stuffed portabello mushrooms",
    "category": "bakery",
    "description": "Homemade baked stuffed portabello mushrooms with spinach and cheese",
    "image": {
      "url": "http://localhost:4000/images/15.jpg",
      "name": ""
    },
    "slug": "baked-stuffed-portabello-mushrooms",
    "stock": 5,
    "price": 20.31,
    "currency": {
      "name": "US Dollar",
      "code": "USD",
      "symbol": "$",
      "symbolNative": "$",
      "decimalDigits": 2,
      "rounding": 0,
      "namePlural": "US dollars"
    },
    "rating": 1,
    "reviews": [],
    "createdAt": {
      "$date": {
        "$numberLong": "1665046691343"
      }
    },
    "updatedAt": {
      "$date": {
        "$numberLong": "1665046691343"
      }
    },
    "discount": null
  },
  {
    "_id": {
      "$oid": "632f3dc1b4f33b52fcc7fa27"
    },
    "title": "Strawberry jelly",
    "category": "fruit",
    "description": "Homemade organic strawberry jelly in a jar",
    "image": {
      "url": "http://localhost:4000/images/16.jpg",
      "name": ""
    },
    "stock": 6,
    "slug": "strawberry-jelly",
    "price": 14.18,
    "currency": {
      "name": "US Dollar",
      "code": "USD",
      "symbol": "$",
      "symbolNative": "$",
      "decimalDigits": 2,
      "rounding": 0,
      "namePlural": "US dollars"
    },
    "rating": 1,
    "reviews": [],
    "createdAt": {
      "$date": {
        "$numberLong": "1665046691343"
      }
    },
    "updatedAt": {
      "$date": {
        "$numberLong": "1665046691343"
      }
    },
    "discount": null
  },
  {
    "_id": {
      "$oid": "632f3dc1b4f33b52fcc7fa28"
    },
    "title": "Pears juice",
    "category": "fruit",
    "description": "Fresh pears juice on the wooden table",
    "slug": "pears-juice",
    "image": {
      "url": "http://localhost:4000/images/17.jpg",
      "name": ""
    },
    "stock": 17,
    "currency": {
      "name": "US Dollar",
      "code": "USD",
      "symbol": "$",
      "symbolNative": "$",
      "decimalDigits": 2,
      "rounding": 0,
      "namePlural": "US dollars"
    },
    "price": 19.49,
    "rating": 4,
    "reviews": [],
    "createdAt": {
      "$date": {
        "$numberLong": "1665046691343"
      }
    },
    "updatedAt": {
      "$date": {
        "$numberLong": "1665046691343"
      }
    },
    "discount": null
  },
  {
    "_id": {
      "$oid": "632f3dc1b4f33b52fcc7fa29"
    },
    "title": "Fresh pears",
    "category": "fruit",
    "description": "Sweet fresh pears on the wooden table",
    "image": {
      "url": "http://localhost:4000/images/18.jpg",
      "name": ""
    },
    "slug": "fresh-pears",
    "stock": 18,
    "price": 15.12,
    "currency": {
      "name": "US Dollar",
      "code": "USD",
      "symbol": "$",
      "symbolNative": "$",
      "decimalDigits": 2,
      "rounding": 0,
      "namePlural": "US dollars"
    },
    "rating": 5,
    "reviews": [],
    "createdAt": {
      "$date": {
        "$numberLong": "1665046691343"
      }
    },
    "updatedAt": {
      "$date": {
        "$numberLong": "1665046691343"
      }
    },
    "discount": null
  },
  {
    "_id": {
      "$oid": "632f3dc1b4f33b52fcc7fa2a"
    },
    "title": "Caprese salad",
    "category": "vegetable",
    "description": "Homemade healthy caprese salad with tomato mozzarella and basil",
    "image": {
      "url": "http://localhost:4000/images/19.jpg",
      "name": ""
    },
    "slug": "caprese-salad",
    "stock": 19,
    "price": 16.76,
    "currency": {
      "name": "US Dollar",
      "code": "USD",
      "symbol": "$",
      "symbolNative": "$",
      "decimalDigits": 2,
      "rounding": 0,
      "namePlural": "US dollars"
    },
    "rating": 5,
    "reviews": [],
    "createdAt": {
      "$date": {
        "$numberLong": "1665046691343"
      }
    },
    "updatedAt": {
      "$date": {
        "$numberLong": "1665046691343"
      }
    },
    "discount": null
  },
  {
    "_id": {
      "$oid": "632f3dc1b4f33b52fcc7fa2b"
    },
    "title": "Oranges",
    "category": "fruit",
    "description": "Orange popsicle ice cream bars made from fresh oranges.  a refreshing summer treat.",
    "image": {
      "url": "http://localhost:4000/images/20.jpg",
      "name": ""
    },
    "stock": 2,
    "slug": "oranges",
    "price": 21.48,
    "currency": {
      "name": "US Dollar",
      "code": "USD",
      "symbol": "$",
      "symbolNative": "$",
      "decimalDigits": 2,
      "rounding": 0,
      "namePlural": "US dollars"
    },
    "rating": 4,
    "reviews": [
      {
        "name": "test21",
        "photoUrl": "http://localhost:4000/images/Avatar-16.png",
        "message": "Nice fruit ",
        "_id": {
          "$oid": "633196203aa06473b2e5ef2f"
        },
        "userId": "632f4b56d9247dba3df502f5"
      },
      {
        "name": "test21",
        "photoUrl": "http://localhost:4000/images/Avatar-16.png",
        "message": "Nice!!!",
        "_id": {
          "$oid": "6331ef3d890f9ed0feb58a47"
        },
        "userId": "632f4b56d9247dba3df502f5"
      }
    ],
    "createdAt": {
      "$date": {
        "$numberLong": "1665046691343"
      }
    },
    "updatedAt": {
      "$date": {
        "$numberLong": "1665051664664"
      }
    },
    "discount": null
  },
  {
    "_id": {
      "$oid": "632f3dc1b4f33b52fcc7fa2c"
    },
    "title": "Vegan food",
    "category": "vegetable",
    "description": "Concept of vegan food",
    "image": {
      "url": "http://localhost:4000/images/21.jpg",
      "name": ""
    },
    "stock": 21,
    "price": 29.66,
    "currency": {
      "name": "US Dollar",
      "code": "USD",
      "symbol": "$",
      "symbolNative": "$",
      "decimalDigits": 2,
      "rounding": 0,
      "namePlural": "US dollars"
    },
    "slug": "vegan-food",
    "rating": 4,
    "reviews": [],
    "createdAt": {
      "$date": {
        "$numberLong": "1665046691343"
      }
    },
    "updatedAt": {
      "$date": {
        "$numberLong": "1665046691343"
      }
    },
    "discount": null
  },
  {
    "_id": {
      "$oid": "632f3dc1b4f33b52fcc7fa2d"
    },
    "title": "Breakfast with muesli",
    "category": "dairy",
    "description": "Concept of healthy breakfast with muesli",
    "image": {
      "url": "http://localhost:4000/images/22.jpg",
      "name": ""
    },
    "stock": 22,
    "slug": "breakfast-with-muesli",
    "price": 22.7,
    "currency": {
      "name": "US Dollar",
      "code": "USD",
      "symbol": "$",
      "symbolNative": "$",
      "decimalDigits": 2,
      "rounding": 0,
      "namePlural": "US dollars"
    },
    "rating": 2,
    "reviews": [],
    "createdAt": {
      "$date": {
        "$numberLong": "1665046691343"
      }
    },
    "updatedAt": {
      "$date": {
        "$numberLong": "1665046691343"
      }
    },
    "discount": null
  },
  {
    "_id": {
      "$oid": "632f3dc1b4f33b52fcc7fa2e"
    },
    "title": "Honey",
    "category": "bakery",
    "description": "Honey and honeycell on the table",
    "image": {
      "url": "http://localhost:4000/images/23.jpg",
      "name": ""
    },
    "slug": "honey",
    "stock": 32,
    "price": 17.01,
    "currency": {
      "name": "US Dollar",
      "code": "USD",
      "symbol": "$",
      "symbolNative": "$",
      "decimalDigits": 2,
      "rounding": 0,
      "namePlural": "US dollars"
    },
    "rating": 2,
    "reviews": [],
    "createdAt": {
      "$date": {
        "$numberLong": "1665046691343"
      }
    },
    "updatedAt": {
      "$date": {
        "$numberLong": "1665046691343"
      }
    },
    "discount": null
  },
  {
    "_id": {
      "$oid": "632f3dc1b4f33b52fcc7fa2f"
    },
    "title": "Breakfast with cottage",
    "category": "fruit",
    "description": "Healthy breakfast with cottage cheese and strawberry",
    "image": {
      "url": "http://localhost:4000/images/24.jpg",
      "name": ""
    },
    "slug": "breakfast-with-cottage",
    "stock": 24,
    "price": 14.05,
    "currency": {
      "name": "US Dollar",
      "code": "USD",
      "symbol": "$",
      "symbolNative": "$",
      "decimalDigits": 2,
      "rounding": 0,
      "namePlural": "US dollars"
    },
    "rating": 1,
    "reviews": [],
    "createdAt": {
      "$date": {
        "$numberLong": "1665046691343"
      }
    },
    "updatedAt": {
      "$date": {
        "$numberLong": "1665046691343"
      }
    },
    "discount": null
  },
  {
    "_id": {
      "$oid": "632f3dc1b4f33b52fcc7fa30"
    },
    "title": "Strawberry smoothie",
    "category": "fruit",
    "description": "Glass of red strawberry smoothie with chia seeds, served with retro cocktail tube, fresh mint and strawberries over dark background",
    "image": {
      "url": "http://localhost:4000/images/25.jpg",
      "name": ""
    },
    "slug": "strawberry-smoothie",
    "stock": 52,
    "price": 28.86,
    "rating": 2,
    "currency": {
      "name": "US Dollar",
      "code": "USD",
      "symbol": "$",
      "symbolNative": "$",
      "decimalDigits": 2,
      "rounding": 0,
      "namePlural": "US dollars"
    },
    "reviews": [],
    "createdAt": {
      "$date": {
        "$numberLong": "1665046691343"
      }
    },
    "updatedAt": {
      "$date": {
        "$numberLong": "1665046691343"
      }
    },
    "discount": null
  },
  {
    "_id": {
      "$oid": "632f3dc1b4f33b52fcc7fa31"
    },
    "title": "Strawberry and mint",
    "category": "fruit",
    "description": "Homemade muesli with strawberry and mint",
    "image": {
      "url": "http://localhost:4000/images/26.jpg",
      "name": ""
    },
    "slug": "strawberry-and-mint",
    "stock": 26,
    "price": 26.21,
    "currency": {
      "name": "US Dollar",
      "code": "USD",
      "symbol": "$",
      "symbolNative": "$",
      "decimalDigits": 2,
      "rounding": 0,
      "namePlural": "US dollars"
    },
    "rating": 4,
    "reviews": [],
    "createdAt": {
      "$date": {
        "$numberLong": "1665046691343"
      }
    },
    "updatedAt": {
      "$date": {
        "$numberLong": "1665046691343"
      }
    },
    "discount": null
  },
  {
    "_id": {
      "$oid": "632f3dc1b4f33b52fcc7fa32"
    },
    "title": "Ricotta",
    "category": "dairy",
    "description": "Ricotta with berry and mint",
    "image": {
      "url": "http://localhost:4000/images/27.jpg",
      "name": ""
    },
    "slug": "ricotta",
    "stock": 27,
    "price": 27.81,
    "currency": {
      "name": "US Dollar",
      "code": "USD",
      "symbol": "$",
      "symbolNative": "$",
      "decimalDigits": 2,
      "rounding": 0,
      "namePlural": "US dollars"
    },
    "rating": 5,
    "reviews": [],
    "createdAt": {
      "$date": {
        "$numberLong": "1665046691343"
      }
    },
    "updatedAt": {
      "$date": {
        "$numberLong": "1665046691343"
      }
    },
    "discount": null
  },
  {
    "_id": {
      "$oid": "632f3dc1b4f33b52fcc7fa33"
    },
    "title": "Cuban sandwiche",
    "category": "bakery",
    "description": "Homemade traditional cuban sandwiches with ham pork and cheese",
    "image": {
      "url": "http://localhost:4000/images/28.jpg",
      "name": ""
    },
    "stock": 28,
    "price": 18.5,
    "slug": "cuban-sandwiche",
    "currency": {
      "name": "US Dollar",
      "code": "USD",
      "symbol": "$",
      "symbolNative": "$",
      "decimalDigits": 2,
      "rounding": 0,
      "namePlural": "US dollars"
    },
    "rating": 4,
    "reviews": [],
    "createdAt": {
      "$date": {
        "$numberLong": "1665046691343"
      }
    },
    "updatedAt": {
      "$date": {
        "$numberLong": "1665046691343"
      }
    },
    "discount": null
  },
  {
    "_id": {
      "$oid": "632f3dc1b4f33b52fcc7fa34"
    },
    "title": "Granola",
    "category": "dairy",
    "description": "Glass jar with homemade granola and yogurt with nuts, raspberries and blackberries on wooden cutting board over white textile in day light",
    "image": {
      "url": "http://localhost:4000/images/29.jpg",
      "name": ""
    },
    "slug": "granola",
    "stock": 29,
    "price": 29.97,
    "currency": {
      "name": "US Dollar",
      "code": "USD",
      "symbol": "$",
      "symbolNative": "$",
      "decimalDigits": 2,
      "rounding": 0,
      "namePlural": "US dollars"
    },
    "rating": 3,
    "reviews": [],
    "createdAt": {
      "$date": {
        "$numberLong": "1665046691343"
      }
    },
    "updatedAt": {
      "$date": {
        "$numberLong": "1665046691343"
      }
    },
    "discount": null
  },
  {
    "_id": {
      "$oid": "632f3dc1b4f33b52fcc7fa35"
    },
    "title": "Smoothie with chia seeds",
    "category": "fruit",
    "description": "Glass of red strawberry smoothie with chia seeds, served with retro cocktail tube, fresh mint and strawberries over wooden table",
    "image": {
      "url": "http://localhost:4000/images/30.jpg",
      "name": ""
    },
    "stock": 30,
    "slug": "smoothie-with-chia-seeds",
    "price": 25.26,
    "currency": {
      "name": "US Dollar",
      "code": "USD",
      "symbol": "$",
      "symbolNative": "$",
      "decimalDigits": 2,
      "rounding": 0,
      "namePlural": "US dollars"
    },
    "rating": 5,
    "reviews": [],
    "createdAt": {
      "$date": {
        "$numberLong": "1665046691343"
      }
    },
    "updatedAt": {
      "$date": {
        "$numberLong": "1665046691343"
      }
    },
    "discount": null
  },
  {
    "_id": {
      "$oid": "632f3dc1b4f33b52fcc7fa36"
    },
    "title": "Yogurt",
    "category": "dairy",
    "description": "Homemade yogurt with raspberry and mint",
    "image": {
      "url": "http://localhost:4000/images/31.jpg",
      "name": ""
    },
    "slug": "yogurt",
    "stock": 5,
    "price": 27.61,
    "currency": {
      "name": "US Dollar",
      "code": "USD",
      "symbol": "$",
      "symbolNative": "$",
      "decimalDigits": 2,
      "rounding": 0,
      "namePlural": "US dollars"
    },
    "rating": 4,
    "reviews": [],
    "createdAt": {
      "$date": {
        "$numberLong": "1665046691343"
      }
    },
    "updatedAt": {
      "$date": {
        "$numberLong": "1665046691343"
      }
    },
    "discount": null
  },
  {
    "_id": {
      "$oid": "632f3dc1b4f33b52fcc7fa37"
    },
    "title": "Sandwich with salad",
    "category": "vegetable",
    "description": "Vegan sandwich with salad, tomato and radish",
    "image": {
      "url": "http://localhost:4000/images/32.jpg",
      "name": ""
    },
    "slug": "sandwich-with-salad",
    "stock": 23,
    "price": 22.48,
    "currency": {
      "name": "US Dollar",
      "code": "USD",
      "symbol": "$",
      "symbolNative": "$",
      "decimalDigits": 2,
      "rounding": 0,
      "namePlural": "US dollars"
    },
    "rating": 5,
    "reviews": [],
    "createdAt": {
      "$date": {
        "$numberLong": "1665046691343"
      }
    },
    "updatedAt": {
      "$date": {
        "$numberLong": "1665046691343"
      }
    },
    "discount": null
  },
  {
    "_id": {
      "$oid": "632f3dc1b4f33b52fcc7fa38"
    },
    "title": "Cherry",
    "category": "fruit",
    "description": "Cherry with sugar on old table",
    "slug": "cherry",
    "image": {
      "url": "http://localhost:4000/images/33.jpg",
      "name": ""
    },
    "stock": 33,
    "price": 14.35,
    "currency": {
      "name": "US Dollar",
      "code": "USD",
      "symbol": "$",
      "symbolNative": "$",
      "decimalDigits": 2,
      "rounding": 0,
      "namePlural": "US dollars"
    },
    "rating": 5,
    "reviews": [],
    "createdAt": {
      "$date": {
        "$numberLong": "1665046691343"
      }
    },
    "updatedAt": {
      "$date": {
        "$numberLong": "1665046691343"
      }
    },
    "discount": null
  },
  {
    "_id": {
      "$oid": "632f3dc1b4f33b52fcc7fa39"
    },
    "title": "Raw asparagus",
    "category": "vegetable",
    "description": "Raw fresh asparagus salad with cheese and dressing",
    "image": {
      "url": "http://localhost:4000/images/34.jpg",
      "name": ""
    },
    "slug": "raw-asparagus",
    "stock": 34,
    "price": 22.97,
    "currency": {
      "name": "US Dollar",
      "code": "USD",
      "symbol": "$",
      "symbolNative": "$",
      "decimalDigits": 2,
      "rounding": 0,
      "namePlural": "US dollars"
    },
    "rating": 4,
    "reviews": [],
    "createdAt": {
      "$date": {
        "$numberLong": "1665046691343"
      }
    },
    "updatedAt": {
      "$date": {
        "$numberLong": "1665046691343"
      }
    },
    "discount": null
  },
  {
    "_id": {
      "$oid": "632f3dc1b4f33b52fcc7fa3a"
    },
    "title": "Corn",
    "category": "vegetable",
    "description": "Grilled corn on the cob with salt and butter",
    "image": {
      "url": "http://localhost:4000/images/35.jpg",
      "name": ""
    },
    "slug": "corn",
    "stock": 35,
    "price": 13.55,
    "currency": {
      "name": "US Dollar",
      "code": "USD",
      "symbol": "$",
      "symbolNative": "$",
      "decimalDigits": 2,
      "rounding": 0,
      "namePlural": "US dollars"
    },
    "rating": 2,
    "reviews": [],
    "createdAt": {
      "$date": {
        "$numberLong": "1665046691343"
      }
    },
    "updatedAt": {
      "$date": {
        "$numberLong": "1665046691343"
      }
    },
    "discount": null
  },
  {
    "_id": {
      "$oid": "632f3dc1b4f33b52fcc7fa3b"
    },
    "title": "Vegan",
    "category": "vegan",
    "description": "Concept of healthy vegan eating",
    "image": {
      "name": "",
      "url": "http://localhost:4000/images/36.jpg",
      "_id": {
        "$oid": "63389872d1f6323078fc06f3"
      }
    },
    "slug": "vegan",
    "stock": 36,
    "price": 28.96,
    "currency": {
      "name": "US Dollar",
      "symbol": "$",
      "symbolNative": "$",
      "decimalDigits": 2,
      "rounding": null,
      "code": "USD",
      "namePlural": "US dollars",
      "_id": {
        "$oid": "63389872d1f6323078fc06f4"
      }
    },
    "rating": 5,
    "reviews": [],
    "createdAt": {
      "$date": {
        "$numberLong": "1665046691343"
      }
    },
    "updatedAt": {
      "$date": {
        "$numberLong": "1665046691343"
      }
    },
    "discount": null
  },
  {
    "_id": {
      "$oid": "632f3dc1b4f33b52fcc7fa3c"
    },
    "title": "Fresh blueberries",
    "category": "fruit",
    "description": "Healthy breakfast. berry crumble with fresh blueberries, raspberries, strawberries, almond, walnuts, pecans, yogurt, and mint in ceramic plates over white wooden surface, top view",
    "image": {
      "url": "http://localhost:4000/images/37.jpg",
      "name": ""
    },
    "stock": 32,
    "slug": "fresh-blueberries",
    "price": 21.01,
    "currency": {
      "name": "US Dollar",
      "code": "USD",
      "symbol": "$",
      "symbolNative": "$",
      "decimalDigits": 2,
      "rounding": 0,
      "namePlural": "US dollars"
    },
    "rating": 4,
    "reviews": [],
    "createdAt": {
      "$date": {
        "$numberLong": "1665046691343"
      }
    },
    "updatedAt": {
      "$date": {
        "$numberLong": "1665046691343"
      }
    },
    "discount": null
  },
  {
    "_id": {
      "$oid": "632f3dc1b4f33b52fcc7fa3d"
    },
    "title": "Smashed avocado",
    "category": "fruit",
    "description": "Vegan sandwiches with smashed avocado, tomatoes and radish. top view",
    "image": {
      "url": "http://localhost:4000/images/38.jpg",
      "name": ""
    },
    "slug": "smashed-avocado",
    "stock": 38,
    "price": 25.88,
    "currency": {
      "name": "US Dollar",
      "code": "USD",
      "symbol": "$",
      "symbolNative": "$",
      "decimalDigits": 2,
      "rounding": 0,
      "namePlural": "US dollars"
    },
    "rating": 0,
    "reviews": [],
    "createdAt": {
      "$date": {
        "$numberLong": "1665046691343"
      }
    },
    "updatedAt": {
      "$date": {
        "$numberLong": "1665046691343"
      }
    },
    "discount": null
  },
  {
    "_id": {
      "$oid": "632f3dc1b4f33b52fcc7fa3e"
    },
    "title": "Italian ciabatta",
    "category": "bakery",
    "description": "Italian ciabatta bread cut in slices on wooden chopping board with herbs, garlic and olives over dark grunge backdrop, top view",
    "image": {
      "url": "http://localhost:4000/images/39.jpg",
      "name": ""
    },
    "slug": "italian-ciabatta",
    "stock": 39,
    "price": 15.18,
    "currency": {
      "name": "US Dollar",
      "code": "USD",
      "symbol": "$",
      "symbolNative": "$",
      "decimalDigits": 2,
      "rounding": 0,
      "namePlural": "US dollars"
    },
    "rating": 1,
    "reviews": [],
    "createdAt": {
      "$date": {
        "$numberLong": "1665046691343"
      }
    },
    "updatedAt": {
      "$date": {
        "$numberLong": "1665046691343"
      }
    },
    "discount": null
  },
  {
    "_id": {
      "$oid": "632f3dc1b4f33b52fcc7fa3f"
    },
    "title": "Rustic breakfast",
    "category": "dairy",
    "description": "Rustic healthy breakfast set. cooked buckwheat groats with milk and honey on dark grunge backdrop. top view, copy space",
    "image": {
      "url": "http://localhost:4000/images/40.jpg",
      "name": ""
    },
    "stock": 40,
    "slug": "rustic-breakfast",
    "price": 21.32,
    "currency": {
      "name": "US Dollar",
      "code": "USD",
      "symbol": "$",
      "symbolNative": "$",
      "decimalDigits": 2,
      "rounding": 0,
      "namePlural": "US dollars"
    },
    "rating": 0,
    "reviews": [],
    "createdAt": {
      "$date": {
        "$numberLong": "1665046691343"
      }
    },
    "updatedAt": {
      "$date": {
        "$numberLong": "1665046691343"
      }
    },
    "discount": null
  },
  {
    "_id": {
      "$oid": "632f3dc1b4f33b52fcc7fa40"
    },
    "title": "Sliced lemons",
    "category": "fruit",
    "description": "Heap of whole and sliced lemons and limes with mint in vintage metal grid box over old wooden table with turquoise wooden background. dark rustic style.",
    "image": {
      "url": "http://localhost:4000/images/41.jpg",
      "name": ""
    },
    "slug": "sliced-lemons",
    "stock": 14,
    "price": 27.14,
    "currency": {
      "name": "US Dollar",
      "code": "USD",
      "symbol": "$",
      "symbolNative": "$",
      "decimalDigits": 2,
      "rounding": 0,
      "namePlural": "US dollars"
    },
    "rating": 2,
    "reviews": [],
    "createdAt": {
      "$date": {
        "$numberLong": "1665046691343"
      }
    },
    "updatedAt": {
      "$date": {
        "$numberLong": "1665046691343"
      }
    },
    "discount": null
  },
  {
    "_id": {
      "$oid": "632f3dc1b4f33b52fcc7fa41"
    },
    "title": "Plums",
    "category": "fruit",
    "description": "Yellow and red sweet plums",
    "image": {
      "url": "http://localhost:4000/images/42.jpg",
      "name": ""
    },
    "slug": "plums",
    "stock": 24,
    "price": 19.18,
    "currency": {
      "name": "US Dollar",
      "code": "USD",
      "symbol": "$",
      "symbolNative": "$",
      "decimalDigits": 2,
      "rounding": 0,
      "namePlural": "US dollars"
    },
    "rating": 1,
    "reviews": [],
    "createdAt": {
      "$date": {
        "$numberLong": "1665046691343"
      }
    },
    "updatedAt": {
      "$date": {
        "$numberLong": "1665046691343"
      }
    },
    "discount": null
  },
  {
    "_id": {
      "$oid": "632f3dc1b4f33b52fcc7fa42"
    },
    "title": "French fries",
    "category": "bakery",
    "description": "Homemade oven baked french fries with ketchup",
    "image": {
      "url": "http://localhost:4000/images/43.jpg",
      "name": ""
    },
    "slug": "french-fries",
    "stock": 43,
    "price": 18.32,
    "currency": {
      "name": "US Dollar",
      "code": "USD",
      "symbol": "$",
      "symbolNative": "$",
      "decimalDigits": 2,
      "rounding": 0,
      "namePlural": "US dollars"
    },
    "rating": 3,
    "reviews": [],
    "createdAt": {
      "$date": {
        "$numberLong": "1665046691343"
      }
    },
    "updatedAt": {
      "$date": {
        "$numberLong": "1665046691343"
      }
    },
    "discount": null
  },
  {
    "_id": {
      "$oid": "632f3dc1b4f33b52fcc7fa43"
    },
    "title": "Strawberries",
    "category": "fruit",
    "description": "Healthy breakfast set. rice cereal or porridge with fresh strawberry, apricots, almond and honey over white rustic wood backdrop, top view, x00",
    "image": {
      "url": "http://localhost:4000/images/44.jpg",
      "name": ""
    },
    "slug": "strawberries",
    "stock": 44,
    "price": 15.13,
    "currency": {
      "name": "US Dollar",
      "code": "USD",
      "symbol": "$",
      "symbolNative": "$",
      "decimalDigits": 2,
      "rounding": 0,
      "namePlural": "US dollars"
    },
    "rating": 3,
    "reviews": [],
    "createdAt": {
      "$date": {
        "$numberLong": "1665046691343"
      }
    },
    "updatedAt": {
      "$date": {
        "$numberLong": "1665046691343"
      }
    },
    "discount": null
  },
  {
    "_id": {
      "$oid": "632f3dc1b4f33b52fcc7fa44"
    },
    "title": "Ground beef meat burger",
    "category": "meat",
    "description": "Raw ground beef meat burger steak cutlets with seasoning on vintage wooden boards, black background",
    "image": {
      "url": "http://localhost:4000/images/45.jpg",
      "name": ""
    },
    "slug": "ground-beef-meat-burger",
    "stock": 45,
    "price": 11.73,
    "currency": {
      "name": "US Dollar",
      "code": "USD",
      "symbol": "$",
      "symbolNative": "$",
      "decimalDigits": 2,
      "rounding": 0,
      "namePlural": "US dollars"
    },
    "rating": 5,
    "reviews": [],
    "createdAt": {
      "$date": {
        "$numberLong": "1665046691343"
      }
    },
    "updatedAt": {
      "$date": {
        "$numberLong": "1665046691343"
      }
    },
    "discount": null
  },
  {
    "_id": {
      "$oid": "632f3dc1b4f33b52fcc7fa45"
    },
    "title": "Tomatoes",
    "category": "fruit",
    "description": "Organic tomatoes made with love",
    "slug": "tomatoes",
    "image": {
      "url": "http://localhost:4000/images/46.jpg",
      "name": ""
    },
    "stock": 64,
    "price": 26.03,
    "currency": {
      "name": "US Dollar",
      "code": "USD",
      "symbol": "$",
      "symbolNative": "$",
      "decimalDigits": 2,
      "rounding": 0,
      "namePlural": "US dollars"
    },
    "rating": 4,
    "reviews": [],
    "createdAt": {
      "$date": {
        "$numberLong": "1665046691343"
      }
    },
    "updatedAt": {
      "$date": {
        "$numberLong": "1665046691343"
      }
    },
    "discount": null
  },
  {
    "_id": {
      "$oid": "632f3dc1b4f33b52fcc7fa46"
    },
    "title": "Basil",
    "category": "vegetable",
    "description": "Concept of vegan food with basil",
    "slug": "basil",
    "image": {
      "url": "http://localhost:4000/images/47.jpg",
      "name": ""
    },
    "stock": 47,
    "price": 15.19,
    "currency": {
      "name": "US Dollar",
      "code": "USD",
      "symbol": "$",
      "symbolNative": "$",
      "decimalDigits": 2,
      "rounding": 0,
      "namePlural": "US dollars"
    },
    "rating": 4,
    "reviews": [],
    "createdAt": {
      "$date": {
        "$numberLong": "1665046691343"
      }
    },
    "updatedAt": {
      "$date": {
        "$numberLong": "1665046691343"
      }
    },
    "discount": null
  },
  {
    "_id": {
      "$oid": "632f3dc1b4f33b52fcc7fa47"
    },
    "title": "Fruits bouquet",
    "category": "fruit",
    "slug": "fruits-bouquet",
    "description": "Abstract citrus fruits bouquet on blue background",
    "image": {
      "url": "http://localhost:4000/images/48.jpg",
      "name": ""
    },
    "stock": 48,
    "price": 18.18,
    "currency": {
      "name": "US Dollar",
      "code": "USD",
      "symbol": "$",
      "symbolNative": "$",
      "decimalDigits": 2,
      "rounding": 0,
      "namePlural": "US dollars"
    },
    "rating": 1,
    "reviews": [],
    "createdAt": {
      "$date": {
        "$numberLong": "1665046691343"
      }
    },
    "updatedAt": {
      "$date": {
        "$numberLong": "1665046691343"
      }
    },
    "discount": null
  },
  {
    "_id": {
      "$oid": "632f3dc1b4f33b52fcc7fa48"
    },
    "title": "Peaches on branch",
    "category": "fruit",
    "slug": "peaches-on-branch",
    "description": "Peaches on branch with leaves and glasses with peach juice and limonade with ice cubes in aluminum tray over old metal table. dark rustic style. top view.",
    "image": {
      "url": "http://localhost:4000/images/49.jpg",
      "name": ""
    },
    "stock": 49,
    "price": 25.62,
    "currency": {
      "name": "US Dollar",
      "code": "USD",
      "symbol": "$",
      "symbolNative": "$",
      "decimalDigits": 2,
      "rounding": 0,
      "namePlural": "US dollars"
    },
    "rating": 3,
    "reviews": [],
    "createdAt": {
      "$date": {
        "$numberLong": "1665046691343"
      }
    },
    "updatedAt": {
      "$date": {
        "$numberLong": "1665046691343"
      }
    },
    "discount": null
  },
  {
    "_id": {
      "$oid": "6340306521a63cf754f81aa6"
    },
    "title": "Textfood",
    "slug": "textfood",
    "category": "vegan",
    "description": "testing the image support",
    "image": {
      "name": "iBB5m-ant-man-and-the-wasp-3840x2160-artwork-4k-19690.jpg",
      "url": "http://localhost:4000/images/iBB5m-ant-man-and-the-wasp-3840x2160-artwork-4k-19690.jpg",
      "_id": {
        "$oid": "6340cc44abd6d7f2a83f12ae"
      }
    },
    "price": 12,
    "stock": 21,
    "rating": 0,
    "currency": {
      "name": "US Dollar",
      "symbol": "$",
      "symbolNative": "$",
      "decimalDigits": 2,
      "rounding": null,
      "code": "USD",
      "namePlural": "US dollars",
      "_id": {
        "$oid": "6340cc44abd6d7f2a83f12af"
      }
    },
    "reviews": [],
    "createdAt": {
      "$date": {
        "$numberLong": "1665151077340"
      }
    },
    "updatedAt": {
      "$date": {
        "$numberLong": "1665190980446"
      }
    },
    "discount": null
  },
  {
    "_id": {
      "$oid": "634954ae23f29b95881ece1e"
    },
    "title": "unknow",
    "slug": "unknow",
    "category": "vegan",
    "description": "hello world",
    "image": {
      "name": "Aerj_-far_cry_3_2012_video_game-wallpaper-2560x1440.jpg",
      "url": "http://localhost:4000/images/Aerj_-far_cry_3_2012_video_game-wallpaper-2560x1440.jpg",
      "_id": {
        "$oid": "634954ae23f29b95881ece1f"
      }
    },
    "price": 21,
    "stock": 0,
    "rating": 0,
    "currency": {
      "name": "US Dollar",
      "symbol": "$",
      "symbolNative": "$",
      "decimalDigits": 2,
      "rounding": null,
      "code": "USD",
      "namePlural": "US dollars",
      "_id": {
        "$oid": "634954ae23f29b95881ece20"
      }
    },
    "reviews": [],
    "createdAt": {
      "$date": {
        "$numberLong": "1665750190464"
      }
    },
    "updatedAt": {
      "$date": {
        "$numberLong": "1665750190464"
      }
    },
    "discount": null
  }
]